graphs_Gamebox62/__init__.py
graphs_Gamebox62/heapq.py
graphs_Gamebox62/sp.py
graphs_gamebox62-0.0.1.dist-info/METADATA
graphs_gamebox62-0.0.1.dist-info/WHEEL
graphs_gamebox62-0.0.1.dist-info/RECORD
