Metadata-Version: 2.3
Name: graphs_Gamebox62
Version: 0.0.1
Summary: Dijkstra Shortest Path
Project-URL: Homepage, https://github.com/Gamebox62/HW6Dijkstra-sShortestPath
Author-email: Derick <dwiggin7@msudenver.edu>
Classifier: License :: OSI Approved :: MIT License
Classifier: Operating System :: OS Independent
Classifier: Programming Language :: Python :: 3
Requires-Python: >=3.7
